gdapi_py/__init__.py
gdapi_py/gdapi_py.py
gdapi_py-1.0.0b2.dist-info/LICENSE.txt
gdapi_py-1.0.0b2.dist-info/METADATA
gdapi_py-1.0.0b2.dist-info/WHEEL
gdapi_py-1.0.0b2.dist-info/top_level.txt
gdapi_py-1.0.0b2.dist-info/RECORD
