Metadata-Version: 2.1
Name: gdapi-py
Version: 1.0.0b2
Summary: Geometry Dash API in Python, for developers.
Home-page: https://github.com/Xytriza/gdapi-py
Author: Xytriza
Author-email: cryfxreal@gmail.com
Classifier: Programming Language :: Python :: 3
Classifier: License :: OSI Approved :: MIT License
Classifier: Operating System :: OS Independent
Requires-Python: >=3.11
License-File: LICENSE.txt
Requires-Dist: requests
